{   
    "frames": {
        "tree_round.png": {
            "frame": {"x":229,"y":15,"w":552,"h":893},
            "rotated": false,
            "trimmed": false,
            "spriteSourceSize": {"x":229,"y":15,"w":552,"h":893},
            "sourceSize": {"w":552,"h":893}
        },
        "tree_triangle.png": {
            "frame": {"x":1047,"y":0,"w":252,"h":776},
            "rotated": false,
            "trimmed": false,
            "spriteSourceSize": {"x":1047,"y":0,"w":252,"h":776},
            "sourceSize": {"w":252,"h":776}
        },
        "tree_dead.png": {
            "frame": {"x":1726,"y":70,"w":369,"h":577},
            "rotated": false,
            "trimmed": false,
            "spriteSourceSize": {"x":1726,"y":70,"w":369,"h":577},
            "sourceSize": {"w":369,"h":577}
        },
        "bush_1.png": {
            "frame": {"x":1365,"y":58,"w":248,"h":228},
            "rotated": false,
            "trimmed": false,
            "spriteSourceSize": {"x":1365,"y":58,"w":248,"h":228},
            "sourceSize": {"w":248,"h":228}
        },
        "bush_2.png": {
            "frame": {"x":1391,"y":355,"w":214,"h":216},
            "rotated": false,
            "trimmed": false,
            "spriteSourceSize": {"x":1391,"y":355,"w":214,"h":216},
            "sourceSize": {"w":214,"h":216}
        },
        "bush_3.png": {
            "frame": {"x":1349,"y":707,"w":242,"h":177},
            "rotated": false,
            "trimmed": false,
            "spriteSourceSize": {"x":1349,"y":707,"w":242,"h":177},
            "sourceSize": {"w":242,"h":177}
        },
        "flower_red.png": {
            "frame": {"x":2269,"y":58,"w":79,"h":210},
            "rotated": false,
            "trimmed": false,
            "spriteSourceSize": {"x":2269,"y":58,"w":79,"h":210},
            "sourceSize": {"w":79,"h":210}
        },
        "flower_violet.png": {
            "frame": {"x":2255,"y":352,"w":103,"h":207},
            "rotated": false,
            "trimmed": false,
            "spriteSourceSize": {"x":2255,"y":352,"w":103,"h":207},
            "sourceSize": {"w":103,"h":207}
        },
        "flower_yellow.png": {
            "frame": {"x":2261,"y":674,"w":75,"h":166},
            "rotated": false,
            "trimmed": false,
            "spriteSourceSize": {"x":2261,"y":674,"w":75,"h":166},
            "sourceSize": {"w":75,"h":166}
        },
        "flower_white.png": {
            "frame": {"x":2658,"y":731,"w":139,"h":136},
            "rotated": false,
            "trimmed": false,
            "spriteSourceSize": {"x":2658,"y":731,"w":139,"h":136},
            "sourceSize": {"w":139,"h":136}
        },
        "statue.png": {
            "frame": {"x":2462,"y":0,"w":135,"h":155},
            "rotated": false,
            "trimmed": false,
            "spriteSourceSize": {"x":2462,"y":0,"w":135,"h":155},
            "sourceSize": {"w":135,"h":155}
        },
        "rock.png": {
            "frame": {"x":2462,"y":155,"w":95,"h":71},
            "rotated": false,
            "trimmed": false,
            "spriteSourceSize": {"x":2462,"y":155,"w":95,"h":71},
            "sourceSize": {"w":95,"h":71}
        },
        "grass.png": {
            "frame": {"x":2608,"y":132,"w":285,"h":160},
            "rotated": false,
            "trimmed": false,
            "spriteSourceSize": {"x":2608,"y":132,"w":285,"h":160},
            "sourceSize": {"w":285,"h":160}
        },
        "grass_dispersed.png": {
            "frame": {"x":2617,"y":302,"w":233,"h":259},
            "rotated": false,
            "trimmed": false,
            "spriteSourceSize": {"x":2617,"y":302,"w":233,"h":259},
            "sourceSize": {"w":233,"h":259}
        }
    }
}